ultraquery/UltraQuery.py
ultraquery/__init__.py
ultraquery/cli.py
ultraquery/plotengine.py
ultraquery/engine_lib/engine.dll
ultraquery/engine_lib/engine.so
ultraquery/engine_lib/libgcc_s_seh-1.dll
ultraquery/engine_lib/libstdc++-6.dll
ultraquery/engine_lib/libwinpthread-1.dll
ultraquery-0.1.0.dist-info/licenses/LICENSE.txt
ultraquery-0.1.0.dist-info/METADATA
ultraquery-0.1.0.dist-info/WHEEL
ultraquery-0.1.0.dist-info/entry_points.txt
ultraquery-0.1.0.dist-info/top_level.txt
ultraquery-0.1.0.dist-info/RECORD
